setup.py
bongo/__init__.py
bongo/api.py
bongo/core.py
bongo.egg-info/PKG-INFO
bongo.egg-info/SOURCES.txt
bongo.egg-info/dependency_links.txt
bongo.egg-info/requires.txt
bongo.egg-info/top_level.txt