Metadata-Version: 1.0
Name: bongo
Version: 0.2
Summary: An API wrapper for Iowa City's bus data
Home-page: UNKNOWN
Author: Zach Williams
Author-email: hey@zachwill.com
License: MIT
Platform: UNKNOWN
Classifier: Development Status :: 1 - Planning
Classifier: Intended Audience :: Developers
Classifier: Natural Language :: English
Classifier: License :: OSI Approved :: MIT License
Classifier: Programming Language :: Python
Classifier: Programming Language :: Python :: 2.6
Classifier: Programming Language :: Python :: 2.7
